augmenter/__init__.py
augmenter/augmentation.py
augmenter/document_chunker.py
augmenter/utils.py
augmenter/config/default_ollama_options.yaml
augmenter/config/default_ollama_prompt.txt
augmenter/config/default_tgi_params.yaml
augmenter/config/default_tgi_prompt.txt
python_data_augmenter-0.0.4.dist-info/METADATA
python_data_augmenter-0.0.4.dist-info/WHEEL
python_data_augmenter-0.0.4.dist-info/top_level.txt
python_data_augmenter-0.0.4.dist-info/RECORD
