Metadata-Version: 2.4
Name: python-data-augmenter
Version: 0.0.4
Summary: This library provides a set of tools for data augmentation, including text generation, data processing, and integration with multiple AI providers.
Author-email: Marcos Cobo Carrillo <mcobo@cic.es>
Project-URL: CIC, https://cic.es
Project-URL: ELFMo, https://elfmo.eu
Project-URL: Source, https://github.com/CIC-SL/python-data-augmenter
Project-URL: Changelog, https://github.com/CIC-SL/python-data-augmenter/blob/main/CHANGELOG.md
Keywords: Augmentation,GenAI,Data,Analytics,ELFMo
Classifier: Programming Language :: Python :: 3
Classifier: License :: OSI Approved :: MIT License
Classifier: Intended Audience :: Developers
Requires-Python: >=3.9
Requires-Dist: pandas
Requires-Dist: numpy
Requires-Dist: requests
Requires-Dist: tqdm
Requires-Dist: scikit-learn
Requires-Dist: sentence-transformers
Requires-Dist: rich
Requires-Dist: pyyaml
Requires-Dist: langchain-community
Requires-Dist: langchain
Requires-Dist: pymupdf
Requires-Dist: openai
